webpage_to_text/__init__.py
webpage_to_text/cli.py
webpage_to_text/config.py
webpage_to_text/extractor.py
webpage_to_text-0.1.0.dist-info/licenses/LICENSE
webpage_to_text-0.1.0.dist-info/METADATA
webpage_to_text-0.1.0.dist-info/WHEEL
webpage_to_text-0.1.0.dist-info/entry_points.txt
webpage_to_text-0.1.0.dist-info/top_level.txt
webpage_to_text-0.1.0.dist-info/RECORD
