Metadata-Version: 2.4
Name: webpage-to-text
Version: 0.1.0
Summary: LlamaIndex-powered web content extractor for RAG applications
Author-email: Your Name <your.email@example.com>
License: MIT
Project-URL: Homepage, https://github.com/yourusername/webpage-to-text
Project-URL: Repository, https://github.com/yourusername/webpage-to-text
Project-URL: Documentation, https://github.com/yourusername/webpage-to-text#readme
Project-URL: Bug Tracker, https://github.com/yourusername/webpage-to-text/issues
Keywords: web scraping,text extraction,llama-index,RAG,machine learning
Classifier: Development Status :: 3 - Alpha
Classifier: Intended Audience :: Developers
Classifier: License :: OSI Approved :: MIT License
Classifier: Operating System :: OS Independent
Classifier: Programming Language :: Python :: 3
Classifier: Programming Language :: Python :: 3.8
Classifier: Programming Language :: Python :: 3.9
Classifier: Programming Language :: Python :: 3.10
Classifier: Programming Language :: Python :: 3.11
Classifier: Programming Language :: Python :: 3.12
Classifier: Topic :: Software Development :: Libraries :: Python Modules
Classifier: Topic :: Internet :: WWW/HTTP :: Browsers
Classifier: Topic :: Scientific/Engineering :: Artificial Intelligence
Classifier: Topic :: Text Processing :: Markup :: HTML
Requires-Python: >=3.8
License-File: LICENSE
Requires-Dist: llama-index>=0.9.0
Requires-Dist: llama-index-readers-web>=0.1.0
Requires-Dist: beautifulsoup4>=4.10.0
Requires-Dist: requests>=2.25.0
Requires-Dist: PyYAML>=6.0
Provides-Extra: dev
Requires-Dist: pytest>=7.0.0; extra == "dev"
Requires-Dist: pytest-cov>=4.0.0; extra == "dev"
Requires-Dist: black>=23.0.0; extra == "dev"
Requires-Dist: flake8>=6.0.0; extra == "dev"
Requires-Dist: mypy>=1.0.0; extra == "dev"
Requires-Dist: pre-commit>=3.0.0; extra == "dev"
Dynamic: license-file
